examples/__init__.py
examples/schema.py
queryfilter/__init__.py
queryfilter/base.py
queryfilter/birthdayfilters.py
queryfilter/datetimefilter.py
queryfilter/exceptions.py
queryfilter/numberfilters.py
queryfilter/queryfilter.py
queryfilter/schemas.py
queryfilter/selectfilters.py
queryfilter/textfilters.py
queryfilter/tests/__init__.py
queryfilter/tests/base_test_case.py
queryfilter/tests/test_birthdayfilters.py
queryfilter/tests/test_datetimefilter.py
queryfilter/tests/test_exceptions.py
queryfilter/tests/test_graphql_schema.py
queryfilter/tests/test_nested_filter.py
queryfilter/tests/test_numberfilters.py
queryfilter/tests/test_queryfilter.py
queryfilter/tests/test_selectfilters.py
queryfilter/tests/test_textfilters.py
queryfilter-0.6.0.dist-info/LICENSE
queryfilter-0.6.0.dist-info/METADATA
queryfilter-0.6.0.dist-info/WHEEL
queryfilter-0.6.0.dist-info/top_level.txt
queryfilter-0.6.0.dist-info/RECORD
