Metadata-Version: 2.1
Name: queryfilter
Version: 0.6.0
Summary: Allow same query interface to be shared between Django ORM,SQLAlchemy, and GraphQL backend.
Home-page: https://github.com/iCHEF/queryfilter
License: License :: OSI Approved :: Apache Software License
Platform: UNKNOWN
Classifier: Development Status :: 2 - Pre-Alpha
Classifier: Topic :: Database :: Front-Ends
Classifier: License :: OSI Approved :: Apache Software License
Classifier: Programming Language :: Python :: 3
Classifier: Programming Language :: Python :: 3.6
Requires-Dist: graphene (<3,>=2.0.1)
Requires-Dist: python-dateutil
Provides-Extra: dev
Requires-Dist: pytest ; extra == 'dev'
Requires-Dist: coverage ; extra == 'dev'
Requires-Dist: pytest-cov ; extra == 'dev'
Requires-Dist: flake8 ; extra == 'dev'
Requires-Dist: pytest-flake8 ; extra == 'dev'
Requires-Dist: tox ; extra == 'dev'
Requires-Dist: django ; extra == 'dev'
